<?xml version="1.0" encoding="utf-8"?>
<results ts="11/6/2012 10:53:14 PM" nm="2012 General Final" fin="0" bal="0" vot="0" tab="0" cltab="0" pol="1051" clpol="843" stpol="0">
  <choices>
    <choice id="1" tot="1" vot="218845" e="1" />
    <choice id="1" tot="0" pid="15" vot="9004" />
    <choice id="1" tot="0" pid="4" vot="209841" />
    <choice id="2" tot="1" vot="218361" e="-1" />
    <choice id="2" tot="0" pid="2" vot="27776" />
    <choice id="2" tot="0" pid="9" vot="190585" />
    <choice id="3" tot="1" vot="1928" e="-1" />
    <choice id="3" tot="0" pid="5" vot="1928" />
    <choice id="4" tot="1" vot="102" e="-1" />
    <choice id="4" tot="0" pid="11" vot="102" />
    <choice id="5" tot="1" vot="2955" e="-1" />
    <choice id="5" tot="0" pid="7" vot="2955" />
    <choice id="6" tot="1" vot="402" e="-1" />
    <choice id="6" tot="0" pid="3" vot="402" />
    <choice id="7" tot="1" vot="702" e="-1" />
    <choice id="8" tot="1" vot="261419" e="1" />
    <choice id="8" tot="0" pid="15" vot="19596" />
    <choice id="8" tot="0" pid="6" vot="12260" />
    <choice id="8" tot="0" pid="4" vot="229563" />
    <choice id="9" tot="1" vot="152665" e="-1" />
    <choice id="9" tot="0" pid="9" vot="127116" />
    <choice id="9" tot="0" pid="2" vot="25549" />
    <choice id="10" tot="1" vot="1679" e="-1" />
    <choice id="10" tot="0" pid="5" vot="1679" />
    <choice id="11" tot="1" vot="1981" e="-1" />
    <choice id="11" tot="0" pid="7" vot="1981" />
    <choice id="12" tot="1" vot="1597" e="-1" />
    <choice id="12" tot="0" pid="1" vot="1597" />
    <choice id="13" tot="1" vot="84" e="-1" />
    <choice id="14" tot="1" vot="182382" e="1" />
    <choice id="14" tot="0" pid="6" vot="9004" />
    <choice id="14" tot="0" pid="15" vot="13742" />
    <choice id="14" tot="0" pid="4" vot="159636" />
    <choice id="15" tot="1" vot="178204" e="-1" />
    <choice id="15" tot="0" pid="6" vot="8914" />
    <choice id="15" tot="0" pid="4" vot="155706" />
    <choice id="15" tot="0" pid="15" vot="13584" />
    <choice id="16" tot="1" vot="185147" e="1" />
    <choice id="16" tot="0" pid="4" vot="160614" />
    <choice id="16" tot="0" pid="15" vot="14938" />
    <choice id="16" tot="0" pid="6" vot="9595" />
    <choice id="17" tot="1" vot="172008" e="-1" />
    <choice id="17" tot="0" pid="6" vot="8183" />
    <choice id="17" tot="0" pid="15" vot="12681" />
    <choice id="17" tot="0" pid="4" vot="151144" />
    <choice id="18" tot="1" vot="179752" e="-1" />
    <choice id="18" tot="0" pid="6" vot="8690" />
    <choice id="18" tot="0" pid="4" vot="157150" />
    <choice id="18" tot="0" pid="15" vot="13912" />
    <choice id="19" tot="1" vot="174215" e="-1" />
    <choice id="19" tot="0" pid="4" vot="158095" />
    <choice id="19" tot="0" pid="15" vot="16120" />
    <choice id="20" tot="1" vot="192449" e="1" />
    <choice id="20" tot="0" pid="9" vot="158808" />
    <choice id="20" tot="0" pid="2" vot="33641" />
    <choice id="21" tot="1" vot="182903" e="1" />
    <choice id="21" tot="0" pid="9" vot="149167" />
    <choice id="21" tot="0" pid="2" vot="33736" />
    <choice id="22" tot="1" vot="174206" e="-1" />
    <choice id="22" tot="0" pid="2" vot="32108" />
    <choice id="22" tot="0" pid="9" vot="142098" />
    <choice id="23" tot="1" vot="185358" e="1" />
    <choice id="23" tot="0" pid="9" vot="151024" />
    <choice id="23" tot="0" pid="2" vot="34334" />
    <choice id="24" tot="1" vot="179593" e="-1" />
    <choice id="24" tot="0" pid="2" vot="33005" />
    <choice id="24" tot="0" pid="9" vot="146588" />
    <choice id="25" tot="1" vot="190020" e="1" />
    <choice id="25" tot="0" pid="2" vot="32389" />
    <choice id="25" tot="0" pid="6" vot="8687" />
    <choice id="25" tot="0" pid="9" vot="148944" />
    <choice id="26" tot="1" vot="503" e="-1" />
    <choice id="27" tot="1" vot="365027" e="1" />
    <choice id="27" tot="0" pid="4" vot="173736" />
    <choice id="27" tot="0" pid="2" vot="31701" />
    <choice id="27" tot="0" pid="6" vot="11511" />
    <choice id="27" tot="0" pid="9" vot="148079" />
    <choice id="28" tot="1" vot="344542" e="1" />
    <choice id="28" tot="0" pid="9" vot="141140" />
    <choice id="28" tot="0" pid="4" vot="161027" />
    <choice id="28" tot="0" pid="2" vot="30991" />
    <choice id="28" tot="0" pid="6" vot="11384" />
    <choice id="29" tot="1" vot="628" e="-1" />
    <choice id="30" tot="1" vot="176570" e="-1" />
    <choice id="30" tot="0" pid="4" vot="176570" />
    <choice id="31" tot="1" vot="196287" e="1" />
    <choice id="31" tot="0" pid="2" vot="32420" />
    <choice id="31" tot="0" pid="6" vot="10102" />
    <choice id="31" tot="0" pid="9" vot="153765" />
    <choice id="32" tot="1" vot="124" e="-1" />
    <choice id="33" tot="1" vot="106743" e="1" />
    <choice id="33" tot="0" pid="4" vot="98418" />
    <choice id="33" tot="0" pid="15" vot="8325" />
    <choice id="34" tot="1" vot="99616" e="-1" />
    <choice id="34" tot="0" pid="2" vot="15014" />
    <choice id="34" tot="0" pid="6" vot="3653" />
    <choice id="34" tot="0" pid="9" vot="80949" />
    <choice id="35" tot="1" vot="139" e="-1" />
    <choice id="36" tot="1" vot="53850" e="-1" />
    <choice id="36" tot="0" pid="15" vot="3776" />
    <choice id="36" tot="0" pid="4" vot="50074" />
    <choice id="37" tot="1" vot="72574" e="1" />
    <choice id="37" tot="0" pid="6" vot="3669" />
    <choice id="37" tot="0" pid="9" vot="58072" />
    <choice id="37" tot="0" pid="2" vot="10833" />
    <choice id="38" tot="1" vot="49" e="-1" />
    <choice id="39" tot="1" vot="44936" e="1" />
    <choice id="39" tot="0" pid="6" vot="2035" />
    <choice id="39" tot="0" pid="15" vot="2227" />
    <choice id="39" tot="0" pid="4" vot="40674" />
    <choice id="40" tot="1" vot="33555" e="-1" />
    <choice id="40" tot="0" pid="9" vot="28081" />
    <choice id="40" tot="0" pid="2" vot="5474" />
    <choice id="41" tot="1" vot="405" e="-1" />
    <choice id="41" tot="0" pid="7" vot="405" />
    <choice id="42" tot="1" vot="90" e="-1" />
    <choice id="42" tot="0" pid="3" vot="90" />
    <choice id="43" tot="1" vot="18" e="-1" />
    <choice id="44" tot="1" vot="40165" e="-1" />
    <choice id="44" tot="0" pid="4" vot="36695" />
    <choice id="44" tot="0" pid="15" vot="3470" />
    <choice id="45" tot="1" vot="61180" e="1" />
    <choice id="45" tot="0" pid="9" vot="49458" />
    <choice id="45" tot="0" pid="2" vot="8411" />
    <choice id="45" tot="0" pid="6" vot="3311" />
    <choice id="46" tot="1" vot="26" e="-1" />
    <choice id="47" tot="1" vot="29591" e="-1" />
    <choice id="47" tot="0" pid="4" vot="29591" />
    <choice id="48" tot="1" vot="64426" e="1" />
    <choice id="48" tot="0" pid="6" vot="3464" />
    <choice id="48" tot="0" pid="2" vot="8523" />
    <choice id="48" tot="0" pid="9" vot="52439" />
    <choice id="49" tot="1" vot="38" e="-1" />
    <choice id="50" tot="1" vot="25631" e="-1" />
    <choice id="50" tot="0" pid="4" vot="25631" />
    <choice id="51" tot="1" vot="33986" e="1" />
    <choice id="51" tot="0" pid="6" vot="1965" />
    <choice id="51" tot="0" pid="9" vot="26749" />
    <choice id="51" tot="0" pid="2" vot="5272" />
    <choice id="52" tot="1" vot="30" e="-1" />
    <choice id="53" tot="1" vot="36658" e="-1" />
    <choice id="53" tot="0" pid="4" vot="33900" />
    <choice id="53" tot="0" pid="15" vot="2758" />
    <choice id="54" tot="1" vot="45604" e="1" />
    <choice id="54" tot="0" pid="2" vot="6635" />
    <choice id="54" tot="0" pid="9" vot="36821" />
    <choice id="54" tot="0" pid="6" vot="2148" />
    <choice id="55" tot="1" vot="25" e="-1" />
    <choice id="56" tot="1" vot="18711" e="-1" />
    <choice id="56" tot="0" pid="4" vot="18711" />
    <choice id="57" tot="1" vot="28574" e="1" />
    <choice id="57" tot="0" pid="12" vot="251" />
    <choice id="57" tot="0" pid="2" vot="3621" />
    <choice id="57" tot="0" pid="6" vot="1624" />
    <choice id="57" tot="0" pid="9" vot="23078" />
    <choice id="58" tot="1" vot="17" e="-1" />
    <choice id="59" tot="1" vot="6243" e="-1" />
    <choice id="59" tot="0" pid="4" vot="6243" />
    <choice id="60" tot="1" vot="8467" e="1" />
    <choice id="60" tot="0" pid="6" vot="455" />
    <choice id="60" tot="0" pid="2" vot="1219" />
    <choice id="60" tot="0" pid="9" vot="6718" />
    <choice id="60" tot="0" pid="12" vot="75" />
    <choice id="61" tot="1" vot="5" e="-1" />
    <choice id="62" tot="1" vot="31092" e="1" />
    <choice id="62" tot="0" pid="15" vot="3586" />
    <choice id="62" tot="0" pid="4" vot="24104" />
    <choice id="62" tot="0" pid="6" vot="3402" />
    <choice id="63" tot="1" vot="171" e="-1" />
    <choice id="64" tot="1" vot="14036" e="-1" />
    <choice id="64" tot="0" pid="4" vot="14036" />
    <choice id="65" tot="1" vot="26904" e="1" />
    <choice id="65" tot="0" pid="9" vot="21401" />
    <choice id="65" tot="0" pid="6" vot="1493" />
    <choice id="65" tot="0" pid="2" vot="4010" />
    <choice id="66" tot="1" vot="5" e="-1" />
    <choice id="67" tot="1" vot="10886" e="1" />
    <choice id="67" tot="0" pid="4" vot="10886" />
    <choice id="68" tot="1" vot="9848" e="-1" />
    <choice id="68" tot="0" pid="6" vot="621" />
    <choice id="68" tot="0" pid="9" vot="7600" />
    <choice id="68" tot="0" pid="2" vot="1627" />
    <choice id="69" tot="1" vot="8" e="-1" />
    <choice id="70" tot="1" vot="21197" e="1" />
    <choice id="70" tot="0" pid="15" vot="1358" />
    <choice id="70" tot="0" pid="4" vot="18899" />
    <choice id="70" tot="0" pid="6" vot="940" />
    <choice id="71" tot="1" vot="13512" e="-1" />
    <choice id="71" tot="0" pid="2" vot="2374" />
    <choice id="71" tot="0" pid="9" vot="11138" />
    <choice id="72" tot="1" vot="10" e="-1" />
    <choice id="73" tot="1" vot="13969" e="-1" />
    <choice id="73" tot="0" pid="4" vot="13969" />
    <choice id="74" tot="1" vot="20195" e="1" />
    <choice id="74" tot="0" pid="2" vot="3275" />
    <choice id="74" tot="0" pid="9" vot="15912" />
    <choice id="74" tot="0" pid="6" vot="1008" />
    <choice id="75" tot="1" vot="16" e="-1" />
    <choice id="76" tot="1" vot="14787" e="1" />
    <choice id="76" tot="0" pid="15" vot="695" />
    <choice id="76" tot="0" pid="6" vot="314" />
    <choice id="76" tot="0" pid="4" vot="13778" />
    <choice id="77" tot="1" vot="3655" e="-1" />
    <choice id="77" tot="0" pid="9" vot="3006" />
    <choice id="77" tot="0" pid="2" vot="649" />
    <choice id="78" tot="1" vot="6" e="-1" />
    <choice id="79" tot="1" vot="16125" e="-1" />
    <choice id="79" tot="0" pid="4" vot="16125" />
    <choice id="80" tot="1" vot="21840" e="1" />
    <choice id="80" tot="0" pid="9" vot="17032" />
    <choice id="80" tot="0" pid="2" vot="3544" />
    <choice id="80" tot="0" pid="8" vot="195" />
    <choice id="80" tot="0" pid="6" vot="1069" />
    <choice id="81" tot="1" vot="7" e="-1" />
    <choice id="82" tot="1" vot="13115" e="-1" />
    <choice id="82" tot="0" pid="4" vot="13115" />
    <choice id="83" tot="1" vot="30902" e="1" />
    <choice id="83" tot="0" pid="6" vot="1369" />
    <choice id="83" tot="0" pid="9" vot="25284" />
    <choice id="83" tot="0" pid="2" vot="4249" />
    <choice id="84" tot="1" vot="9" e="-1" />
    <choice id="85" tot="1" vot="8640" e="-1" />
    <choice id="85" tot="0" pid="4" vot="8640" />
    <choice id="86" tot="1" vot="16217" e="1" />
    <choice id="86" tot="0" pid="2" vot="2289" />
    <choice id="86" tot="0" pid="12" vot="127" />
    <choice id="86" tot="0" pid="9" vot="12981" />
    <choice id="86" tot="0" pid="6" vot="820" />
    <choice id="87" tot="1" vot="12" e="-1" />
    <choice id="88" tot="1" vot="16655" e="-1" />
    <choice id="88" tot="0" pid="4" vot="16655" />
    <choice id="89" tot="1" vot="20156" e="1" />
    <choice id="89" tot="0" pid="15" vot="765" />
    <choice id="89" tot="0" pid="9" vot="15997" />
    <choice id="89" tot="0" pid="2" vot="2435" />
    <choice id="89" tot="0" pid="6" vot="959" />
    <choice id="90" tot="1" vot="12" e="-1" />
    <choice id="91" tot="1" vot="16858" e="1" />
    <choice id="91" tot="0" pid="6" vot="901" />
    <choice id="91" tot="0" pid="15" vot="1357" />
    <choice id="91" tot="0" pid="4" vot="14600" />
    <choice id="92" tot="1" vot="6119" e="-1" />
    <choice id="92" tot="0" pid="9" vot="6119" />
    <choice id="93" tot="1" vot="3" e="-1" />
    <choice id="94" tot="1" vot="28585" e="1" />
    <choice id="94" tot="0" pid="9" vot="20871" />
    <choice id="94" tot="0" pid="2" vot="3752" />
    <choice id="94" tot="0" pid="6" vot="3962" />
    <choice id="95" tot="1" vot="94" e="-1" />
    <choice id="96" tot="1" vot="39781" e="1" />
    <choice id="96" tot="0" pid="9" vot="15330" />
    <choice id="96" tot="0" pid="4" vot="19989" />
    <choice id="96" tot="0" pid="6" vot="1254" />
    <choice id="96" tot="0" pid="2" vot="3208" />
    <choice id="97" tot="1" vot="39744" e="1" />
    <choice id="97" tot="0" pid="2" vot="3285" />
    <choice id="97" tot="0" pid="9" vot="15565" />
    <choice id="97" tot="0" pid="4" vot="19621" />
    <choice id="97" tot="0" pid="6" vot="1273" />
    <choice id="98" tot="1" vot="54" e="-1" />
    <choice id="99" tot="1" vot="33108" e="1" />
    <choice id="99" tot="0" pid="15" vot="1509" />
    <choice id="99" tot="0" pid="6" vot="1349" />
    <choice id="99" tot="0" pid="4" vot="26315" />
    <choice id="99" tot="0" pid="2" vot="3935" />
    <choice id="100" tot="1" vot="12814" e="-1" />
    <choice id="100" tot="0" pid="9" vot="12814" />
    <choice id="101" tot="1" vot="16" e="-1" />
    <choice id="102" tot="1" vot="50299" e="-1" />
    <choice id="102" tot="0" pid="15" vot="4116" />
    <choice id="102" tot="0" pid="4" vot="46183" />
    <choice id="103" tot="1" vot="67210" e="1" />
    <choice id="103" tot="0" pid="9" vot="53747" />
    <choice id="103" tot="0" pid="2" vot="9920" />
    <choice id="103" tot="0" pid="6" vot="3543" />
    <choice id="104" tot="1" vot="72" e="-1" />
    <choice id="105" tot="1" vot="60245" e="1" />
    <choice id="105" tot="0" pid="15" vot="1138" />
    <choice id="105" tot="0" pid="6" vot="1912" />
    <choice id="105" tot="0" pid="4" vot="28272" />
    <choice id="105" tot="0" pid="9" vot="24556" />
    <choice id="105" tot="0" pid="2" vot="4367" />
    <choice id="106" tot="1" vot="88" e="-1" />
    <choice id="107" tot="1" vot="1900" e="-1" />
    <choice id="107" tot="0" pid="13" vot="1900" />
    <choice id="108" tot="1" vot="6188" e="1" />
    <choice id="108" tot="0" pid="10" vot="6188" />
    <choice id="109" tot="1" vot="8" e="-1" />
    <choice id="110" tot="1" vot="9652" e="1" />
    <choice id="110" tot="0" pid="9" vot="7520" />
    <choice id="110" tot="0" pid="2" vot="2132" />
    <choice id="111" tot="1" vot="26" e="-1" />
    <choice id="112" tot="1" vot="0" e="0" />
    <choice id="112" tot="0" pid="4" vot="0" />
    <choice id="112" tot="0" pid="2" vot="0" />
    <choice id="112" tot="0" pid="9" vot="0" />
    <choice id="113" tot="1" vot="0" e="0" />
    <choice id="114" tot="1" vot="16152" e="-1" />
    <choice id="114" tot="0" pid="4" vot="13996" />
    <choice id="114" tot="0" pid="5" vot="316" />
    <choice id="114" tot="0" pid="6" vot="891" />
    <choice id="114" tot="0" pid="15" vot="949" />
    <choice id="115" tot="1" vot="13286" e="-1" />
    <choice id="115" tot="0" pid="4" vot="13286" />
    <choice id="116" tot="1" vot="23140" e="1" />
    <choice id="116" tot="0" pid="2" vot="3819" />
    <choice id="116" tot="0" pid="9" vot="19321" />
    <choice id="117" tot="1" vot="23107" e="1" />
    <choice id="117" tot="0" pid="2" vot="3659" />
    <choice id="117" tot="0" pid="9" vot="18567" />
    <choice id="117" tot="0" pid="6" vot="881" />
    <choice id="118" tot="1" vot="2338" e="-1" />
    <choice id="118" tot="0" pid="15" vot="1714" />
    <choice id="118" tot="0" pid="5" vot="624" />
    <choice id="119" tot="1" vot="12" e="-1" />
    <choice id="120" tot="1" vot="19404" e="1" />
    <choice id="120" tot="0" pid="9" vot="6641" />
    <choice id="120" tot="0" pid="4" vot="10011" />
    <choice id="120" tot="0" pid="6" vot="739" />
    <choice id="120" tot="0" pid="2" vot="1284" />
    <choice id="120" tot="0" pid="15" vot="729" />
    <choice id="121" tot="1" vot="20" e="-1" />
    <choice id="122" tot="1" vot="3096" e="-1" />
    <choice id="122" tot="0" pid="4" vot="3096" />
    <choice id="123" tot="1" vot="4308" e="1" />
    <choice id="123" tot="0" pid="9" vot="3405" />
    <choice id="123" tot="0" pid="6" vot="268" />
    <choice id="123" tot="0" pid="2" vot="635" />
    <choice id="124" tot="1" vot="1" e="-1" />
  </choices>
  <contests>
    <contest id="1001" bal="444983" bl="115" uv="1247" ov="441" wr="0" />
    <contest id="1002" bal="444983" bl="115" uv="24933" ov="625" wr="0" />
    <contest id="1003" bal="444983" bl="115" uv="490830" ov="2328" wr="0" />
    <contest id="1004" bal="444983" bl="115" uv="179661" ov="108" wr="0" />
    <contest id="1005" bal="444983" bl="115" uv="71852" ov="150" wr="0" />
    <contest id="1006" bal="218147" bl="56" uv="11538" ov="111" wr="0" />
    <contest id="1007" bal="142009" bl="43" uv="15459" ov="77" wr="0" />
    <contest id="1008" bal="84827" bl="16" uv="5727" ov="96" wr="0" />
    <contest id="1009" bal="110222" bl="22" uv="8787" ov="64" wr="0" />
    <contest id="1010" bal="104816" bl="23" uv="10704" ov="57" wr="0" />
    <contest id="1011" bal="68477" bl="29" uv="8803" ov="27" wr="0" />
    <contest id="1012" bal="92541" bl="26" uv="10218" ov="36" wr="0" />
    <contest id="1013" bal="52229" bl="12" uv="4905" ov="22" wr="0" />
    <contest id="1014" bal="16698" bl="3" uv="1965" ov="18" wr="0" />
    <contest id="1015" bal="46292" bl="7" uv="15023" ov="6" wr="0" />
    <contest id="1016" bal="46114" bl="12" uv="5160" ov="9" wr="0" />
    <contest id="1017" bal="24055" bl="15" uv="3305" ov="8" wr="0" />
    <contest id="1018" bal="38085" bl="5" uv="3352" ov="14" wr="0" />
    <contest id="1019" bal="40414" bl="11" uv="6226" ov="8" wr="0" />
    <contest id="1020" bal="20195" bl="13" uv="1728" ov="19" wr="0" />
    <contest id="1021" bal="42142" bl="12" uv="4149" ov="21" wr="0" />
    <contest id="1022" bal="50249" bl="13" uv="6202" ov="21" wr="0" />
    <contest id="1023" bal="28867" bl="7" uv="3989" ov="9" wr="0" />
    <contest id="1024" bal="40841" bl="10" uv="3976" ov="42" wr="0" />
    <contest id="1025" bal="26955" bl="3" uv="3956" ov="19" wr="0" />
    <contest id="1026" bal="40774" bl="7" uv="12092" ov="3" wr="0" />
    <contest id="1027" bal="50786" bl="11" uv="21985" ov="8" wr="0" />
    <contest id="1028" bal="50786" bl="11" uv="4812" ov="36" wr="0" />
    <contest id="1029" bal="130129" bl="32" uv="12494" ov="54" wr="0" />
    <contest id="1030" bal="70621" bl="14" uv="10286" ov="2" wr="0" />
    <contest id="1031" bal="13479" bl="8" uv="5372" ov="11" wr="0" />
    <contest id="1032" bal="13479" bl="8" uv="3800" ov="1" wr="0" />
    <contest id="1033" bal="0" bl="0" uv="0" ov="0" wr="0" />
    <contest id="1034" bal="46128" bl="11" uv="14141" ov="80" wr="0" />
    <contest id="1035" bal="22205" bl="5" uv="2778" ov="3" wr="0" />
    <contest id="1036" bal="7842" bl="0" uv="436" ov="1" wr="0" />
  </contests>
  <areas>
    <area id="44" bal="0" vot="0" tab="0" cltab="0" pol="1051" clpol="843" stpol="0" />
    <area id="46" bal="0" vot="0" tab="0" cltab="0" pol="154" clpol="116" stpol="0" />
    <area id="14" bal="0" vot="0" tab="0" cltab="0" pol="295" clpol="224" stpol="0" />
    <area id="9" bal="0" vot="0" tab="0" cltab="0" pol="19" clpol="15" stpol="0" />
    <area id="16" bal="0" vot="0" tab="0" cltab="0" pol="178" clpol="141" stpol="0" />
    <area id="57" bal="0" vot="0" tab="0" cltab="0" pol="226" clpol="193" stpol="0" />
    <area id="47" bal="0" vot="0" tab="0" cltab="0" pol="22" clpol="22" stpol="0" />
    <area id="7" bal="0" vot="0" tab="0" cltab="0" pol="4" clpol="0" stpol="0" />
    <area id="40" bal="0" vot="0" tab="0" cltab="0" pol="92" clpol="81" stpol="0" />
    <area id="51" bal="0" vot="0" tab="0" cltab="0" pol="42" clpol="38" stpol="0" />
    <area id="23" bal="0" vot="0" tab="0" cltab="0" pol="19" clpol="13" stpol="0" />
    <area id="59" bal="0" vot="0" tab="0" cltab="0" pol="369" clpol="298" stpol="0" />
    <area id="22" bal="0" vot="0" tab="0" cltab="0" pol="472" clpol="378" stpol="0" />
    <area id="11" bal="0" vot="0" tab="0" cltab="0" pol="210" clpol="167" stpol="0" />
    <area id="41" bal="0" vot="0" tab="0" cltab="0" pol="225" clpol="185" stpol="0" />
    <area id="58" bal="0" vot="0" tab="0" cltab="0" pol="53" clpol="40" stpol="0" />
    <area id="21" bal="0" vot="0" tab="0" cltab="0" pol="221" clpol="183" stpol="0" />
    <area id="31" bal="0" vot="0" tab="0" cltab="0" pol="212" clpol="182" stpol="0" />
    <area id="43" bal="0" vot="0" tab="0" cltab="0" pol="205" clpol="148" stpol="0" />
    <area id="13" bal="0" vot="0" tab="0" cltab="0" pol="135" clpol="105" stpol="0" />
    <area id="55" bal="0" vot="0" tab="0" cltab="0" pol="64" clpol="60" stpol="0" />
    <area id="26" bal="0" vot="0" tab="0" cltab="0" pol="121" clpol="85" stpol="0" />
    <area id="12" bal="0" vot="0" tab="0" cltab="0" pol="81" clpol="60" stpol="0" />
    <area id="49" bal="0" vot="0" tab="0" cltab="0" pol="105" clpol="86" stpol="0" />
    <area id="2" bal="0" vot="0" tab="0" cltab="0" pol="78" clpol="62" stpol="0" />
    <area id="37" bal="0" vot="0" tab="0" cltab="0" pol="89" clpol="76" stpol="0" />
    <area id="24" bal="0" vot="0" tab="0" cltab="0" pol="72" clpol="44" stpol="0" />
    <area id="30" bal="0" vot="0" tab="0" cltab="0" pol="82" clpol="71" stpol="0" />
    <area id="48" bal="0" vot="0" tab="0" cltab="0" pol="102" clpol="81" stpol="0" />
    <area id="8" bal="0" vot="0" tab="0" cltab="0" pol="90" clpol="78" stpol="0" />
    <area id="17" bal="0" vot="0" tab="0" cltab="0" pol="64" clpol="48" stpol="0" />
    <area id="10" bal="0" vot="0" tab="0" cltab="0" pol="103" clpol="92" stpol="0" />
    <area id="18" bal="0" vot="0" tab="0" cltab="0" pol="51" clpol="40" stpol="0" />
    <area id="4" bal="0" vot="0" tab="0" cltab="0" pol="50" clpol="47" stpol="0" />
    <area id="29" bal="0" vot="0" tab="0" cltab="0" pol="44" clpol="39" stpol="0" />
    <area id="33" bal="0" vot="0" tab="0" cltab="0" pol="49" clpol="35" stpol="0" />
    <area id="1" bal="0" vot="0" tab="0" cltab="0" pol="56" clpol="25" stpol="0" />
    <area id="56" bal="0" vot="0" tab="0" cltab="0" pol="45" clpol="38" stpol="0" />
    <area id="60" bal="0" vot="0" tab="0" cltab="0" pol="11" clpol="11" stpol="0" />
    <area id="38" bal="0" vot="0" tab="0" cltab="0" pol="18" clpol="17" stpol="0" />
    <area id="39" bal="0" vot="0" tab="0" cltab="0" pol="8" clpol="8" stpol="0" />
    <area id="52" bal="0" vot="0" tab="0" cltab="0" pol="945" clpol="755" stpol="0" />
    <area id="45" bal="0" vot="0" tab="0" cltab="0" pol="58" clpol="55" stpol="0" />
    <area id="25" bal="0" vot="0" tab="0" cltab="0" pol="71" clpol="43" stpol="0" />
    <area id="19" bal="0" vot="0" tab="0" cltab="0" pol="51" clpol="30" stpol="0" />
    <area id="36" bal="0" vot="0" tab="0" cltab="0" pol="68" clpol="64" stpol="0" />
    <area id="54" bal="0" vot="0" tab="0" cltab="0" pol="53" clpol="42" stpol="0" />
    <area id="5" bal="0" vot="0" tab="0" cltab="0" pol="53" clpol="49" stpol="0" />
    <area id="28" bal="0" vot="0" tab="0" cltab="0" pol="65" clpol="50" stpol="0" />
    <area id="27" bal="0" vot="0" tab="0" cltab="0" pol="46" clpol="40" stpol="0" />
    <area id="6" bal="0" vot="0" tab="0" cltab="0" pol="55" clpol="20" stpol="0" />
    <area id="35" bal="0" vot="0" tab="0" cltab="0" pol="66" clpol="54" stpol="0" />
    <area id="15" bal="0" vot="0" tab="0" cltab="0" pol="49" clpol="40" stpol="0" />
    <area id="53" bal="0" vot="0" tab="0" cltab="0" pol="63" clpol="55" stpol="0" />
    <area id="32" bal="0" vot="0" tab="0" cltab="0" pol="58" clpol="51" stpol="0" />
    <area id="34" bal="0" vot="0" tab="0" cltab="0" pol="52" clpol="49" stpol="0" />
    <area id="42" bal="0" vot="0" tab="0" cltab="0" pol="75" clpol="56" stpol="0" />
    <area id="20" bal="0" vot="0" tab="0" cltab="0" pol="60" clpol="60" stpol="0" />
    <area id="50" bal="0" vot="0" tab="0" cltab="0" pol="62" clpol="53" stpol="0" />
    <area id="3" bal="0" vot="0" tab="0" cltab="0" pol="46" clpol="32" stpol="0" />
  </areas>
</results>